isec_connect/__init__.py
isec_connect/isec_ws_sdk.py
isec_connect-0.0.2.dist-info/LICENSE
isec_connect-0.0.2.dist-info/METADATA
isec_connect-0.0.2.dist-info/WHEEL
isec_connect-0.0.2.dist-info/top_level.txt
isec_connect-0.0.2.dist-info/RECORD
